<?xml version="1.0" encoding="UTF-8"?>
<QCARConfig xmlns:xsi="http://www.w3.org/2001/XMLSchema-instance" xsi:noNamespaceSchemaLocation="qcar_config.xsd">
  <Tracking>
    <ImageTarget name="chapter-5-quiz-stars" size="5.000000 3.524194" />
    <ImageTarget name="chapter-4-quiz-stars" size="5.000000 3.524194" />
    <ImageTarget name="chapter-3-quiz-stars" size="5.000000 3.524194" />
    <ImageTarget name="chapter-2-quiz-stars" size="5.000000 3.524194" />
    <ImageTarget name="chapter-1-quiz-stars" size="5.000000 3.524194" />
    <ImageTarget name="chapter-5-quiz-3" size="5.000000 3.524194" />
    <ImageTarget name="chapter-4-quiz-3" size="5.000000 3.524194" />
    <ImageTarget name="chapter-3-quiz-3" size="5.000000 3.524194" />
    <ImageTarget name="chapter-2-quiz-3" size="5.000000 3.524194" />
    <ImageTarget name="chapter-1-quiz-3" size="5.000000 3.524194" />
    <ImageTarget name="chapter-5-quiz-2" size="5.000000 3.524194" />
    <ImageTarget name="chapter-4-quiz-2" size="5.000000 3.524194" />
    <ImageTarget name="chapter-3-quiz-2" size="5.000000 3.524194" />
    <ImageTarget name="chapter-2-quiz-2" size="5.000000 3.524194" />
    <ImageTarget name="chapter-1-quiz-2" size="5.000000 3.524194" />
    <ImageTarget name="chapter-5-quiz2" size="5.000000 3.524194" />
    <ImageTarget name="chapter-5-oceania2" size="5.000000 3.524194" />
    <ImageTarget name="chapter-5-chest2" size="5.000000 3.524194" />
    <ImageTarget name="chapter-4-quiz2" size="2.000000 1.409677" />
    <ImageTarget name="chapter-4-memorygame2" size="5.000000 3.524194" />
    <ImageTarget name="chapter-4-dount2" size="5.000000 3.524194" />
    <ImageTarget name="chapter-4-chest2" size="5.000000 3.524194" />
    <ImageTarget name="chapter-4-americas2" size="5.000000 3.524194" />
    <ImageTarget name="chapter-3-europe2" size="5.000000 3.524194" />
    <ImageTarget name="chapter-3-chest2" size="5.000000 3.524194" />
    <ImageTarget name="chapter-5-penguins" size="5.000000 3.524194" />
    <ImageTarget name="chapter-5-coconut" size="5.000000 3.524194" />
    <ImageTarget name="chapter-4-dount" size="5.000000 3.524194" />
    <ImageTarget name="chapter-3-quiz" size="5.000000 3.524194" />
    <ImageTarget name="chapter3-map" size="5.000000 3.524194" />
    <ImageTarget name="chapter-3-boat" size="5.000000 3.524194" />
    <ImageTarget name="chapter-2-quiz" size="5.000000 3.524194" />
    <ImageTarget name="chapter-2-fishing" size="5.000000 3.524194" />
    <ImageTarget name="chapter-2-chest" size="5.000000 3.524194" />
    <ImageTarget name="chapter2-boat" size="5.000000 3.524194" />
    <ImageTarget name="chapter-2-animation" size="5.000000 3.524194" />
    <ImageTarget name="chapter-1-waterwave" size="5.000000 3.524194" />
    <ImageTarget name="chapter1-quiz" size="5.000000 3.524194" />
    <ImageTarget name="chapter1-maze" size="5.000000 3.524194" />
    <ImageTarget name="chapter-1-chest" size="5.000000 3.524194" />
    <ImageTarget name="chapter1-animation" size="5.000000 3.524194" />
    <ImageTarget name="chaper1-collectcoins" size="5.000000 3.521875" />
    <ImageTarget name="WelcomeMeHearty" size="5.000000 3.525000" />
    <ImageTarget name="Contents" size="5.000000 3.523809" />
    <ImageTarget name="UK_10_24bit" size="5.000000 4.791667" />
    <ImageTarget name="UK_7_24bit" size="5.000000 4.761905" />
    <ImageTarget name="UK_4_24bit" size="5.000000 4.971910" />
    <ImageTarget name="UK_1_24bit" size="5.000000 5.050251" />
    <ImageTarget name="TC_10_24bit" size="5.000000 4.766840" />
    <ImageTarget name="TC_7_24bit" size="5.000000 4.716981" />
    <ImageTarget name="TC_4_24bit" size="5.000000 5.028090" />
    <ImageTarget name="TC_1_24bit" size="5.000000 5.050505" />
    <ImageTarget name="TBS_10_24bit" size="5.000000 4.766840" />
    <ImageTarget name="TBS_7_24bit" size="5.000000 4.761905" />
    <ImageTarget name="TBS_4_24bit" size="5.000000 4.887640" />
    <ImageTarget name="TBS_1_24bit" size="5.000000 5.076142" />
    <ImageTarget name="M_10_24bit" size="5.000000 4.791667" />
    <ImageTarget name="M_7_24bit" size="5.000000 4.761905" />
    <ImageTarget name="M_4_24bit" size="5.000000 4.943503" />
    <ImageTarget name="M_1_24bit" size="5.000000 5.050505" />
    <ImageTarget name="L_10_24bit" size="5.000000 4.791667" />
    <ImageTarget name="L_7_24bit" size="5.000000 4.761905" />
    <ImageTarget name="L_4_24bit" size="5.000000 5.028409" />
    <ImageTarget name="L_1_24bit" size="5.000000 5.076142" />
    <ImageTarget name="EE_10_24bit" size="5.000000 4.766840" />
    <ImageTarget name="EE_7_24bit" size="5.000000 4.761905" />
    <ImageTarget name="EE_4_24bit" size="5.000000 4.971910" />
    <ImageTarget name="EE_1_24bit" size="5.000000 5.050505" />
    <ImageTarget name="5_24bit" size="5.000000 6.666667" />
    <ImageTarget name="4_24bit" size="5.000000 7.072581" />
    <ImageTarget name="3_24bit" size="5.000000 7.070565" />
    <ImageTarget name="2_24bit" size="5.000000 7.070565" />
    <ImageTarget name="1_24bit" size="5.000000 7.013802" />
    <ImageTarget name="DSC_0049" size="0.060000 0.042485" />
    <ImageTarget name="DSC_0047" size="0.030000 0.019095" />
    <ImageTarget name="DSC_0046" size="0.010000 0.003361" />
    <ImageTarget name="albania" size="1.000000 0.718801" />
  </Tracking>
</QCARConfig>
